revDeepSeek/__init__.py
revDeepSeek/main.py
revDeepSeek/solve_pow.py
revDeepSeek/wasm/sha3_wasm_bg.7b9ca65ddd.wasm
revdeepseek-0.0.1.dist-info/METADATA
revdeepseek-0.0.1.dist-info/WHEEL
revdeepseek-0.0.1.dist-info/licenses/LICENSE
revdeepseek-0.0.1.dist-info/RECORD
