Metadata-Version: 2.4
Name: revDeepSeek
Version: 0.0.1
Summary: DeepSeek逆向api
Project-URL: Homepage, https://github.com/old-dream321/revDeepSeek
Author-email: old-dream321 <hzz123123@outlook.com>
License: MIT License
License-File: LICENSE
Classifier: License :: OSI Approved :: MIT License
Classifier: Operating System :: OS Independent
Classifier: Programming Language :: Python :: 3
Requires-Python: >=3.9
Requires-Dist: filetype
Requires-Dist: numpy
Requires-Dist: requests
Requires-Dist: wasmtime
